{
    "clntBankAccountNo": null,
    "clntBankBranchCode": null,
    "clntBankCode": "4116",
    "clntBranchCode": "4116",
    "clntCountryCode": "1",
    "clntCountyCode": null,
    "clntCreatedBy": "TQUEST",
    "clntDateCreated": "2025-04-23T15:39:40",
    "clntDob": "1986-01-01",
    "clntEmailAddrs": "test14646.wrk33@gmail.com",
    "clntGender": "M",
    "clntIdRegNo": "13002200",
    "clntMaritalStatus": "S",
    "clntName": "SYLVIA NDUNGU",
    "clntOccupation": null,
    "clntOccupationName": null,
    "clntOtherNames": null,
    "clntPassportNo": null,
    "clntPassword": null,
    "clntPhysicalAddrs": "",
    "clntPin": "Q1234599922K",
    "clntPostalAddrs": "",
    "clntSector": null,
    "clntSmsTel": "0713387260",
    "clntStatus": "A",
    "clntSurname": "SYLVIA NDUNGU",
    "clntTelephoneNumber1": "0713387260",
    "clntTelephoneNumber2": "0713387260",
    "clntTitle": null,
    "clntTownCode": null,
    "clntType": "8100",
    "clntTypeName": "I",
    "clntUpdateDt": null,
    "clntUpdatedBy": null,
    "clntWef": null,
    "clntWet": null,
    "clntpostalCode": null
  }